{"run_number": "1683180651563628", "step_name": "read", "task_id": "2", "attempt_id": 0, "name": "_foreach_stack", "content_type": "gzip+pickle-v2", "type": "metaflow.artifact", "sha": "4ca058df2ea422cca260c585409d6ac9face7ebe", "ds_type": "local", "location": ":root:/home/agilesoda/just-type/metaflow/daisy/.metaflow", "flow_id": "Workflow2_mod3", "user_name": "agilesoda", "tags": [], "system_tags": ["python_version:3.8.16", "metaflow_version:2.8.0", "user:agilesoda", "runtime:dev"], "ts_epoch": 1683180652082}